README.md
setup.py
pumpkin_supmcu/i2cdriver/__init__.py
pumpkin_supmcu/i2cdriver/i2cdriver.py
pumpkin_supmcu_i2cdriver.egg-info/PKG-INFO
pumpkin_supmcu_i2cdriver.egg-info/SOURCES.txt
pumpkin_supmcu_i2cdriver.egg-info/dependency_links.txt
pumpkin_supmcu_i2cdriver.egg-info/not-zip-safe
pumpkin_supmcu_i2cdriver.egg-info/requires.txt
pumpkin_supmcu_i2cdriver.egg-info/top_level.txt